dzo/__init__.py
dzo/_meta.py
dzo/annot.py
dzo/base.py
dzo/const.py
dzo/engine.py
dzo/indexer.py
dzo/mapper.py
dzo/preprocess.py
dzo/types.py
dzo/utility.py
dzo/_cmd/__init__.py
dzo/_cmd/__main__.py
dzo/_cmd/preprocess.py
dzo/_cmd/search.py
dzo/_ext/core.cpython-37m-darwin.so
dzo/loader/__init__.py
dzo/loader/base.py
dzo/loader/directory.py
dzo/tokenizer/__init__.py
dzo/tokenizer/base.py
dzo/tokenizer/mecab.py
dzo/tokenizer/ngram.py
dzo/tokenizer/token.py
dzo/tokenizer/types.py
dzo/tokenizer/whitespace.py
dzo-0.0.7.dist-info/LICENSE
dzo-0.0.7.dist-info/METADATA
dzo-0.0.7.dist-info/WHEEL
dzo-0.0.7.dist-info/entry_points.txt
dzo-0.0.7.dist-info/top_level.txt
dzo-0.0.7.dist-info/RECORD
